setup.py
baibaoxiang/__init__.py
baibaoxiang/baibaoxiang.py
dashu.egg-info/PKG-INFO
dashu.egg-info/SOURCES.txt
dashu.egg-info/dependency_links.txt
dashu.egg-info/top_level.txt