Metadata-Version: 1.0
Name: dashu
Version: 1.0.1
Summary: time and path tool
Home-page: https://baidu.com
Author: dashu
Author-email: bj_xiaoya@163.com
License: MIT Licence
Keywords: pip,pathtool,timetool,magetool,mage
Platform: any
